opengui.py
opengui-0.9.8.dist-info/LICENSE.txt
opengui-0.9.8.dist-info/METADATA
opengui-0.9.8.dist-info/WHEEL
opengui-0.9.8.dist-info/top_level.txt
opengui-0.9.8.dist-info/RECORD
