Metadata-Version: 2.1
Name: opengui
Version: 0.9.8
Summary: Library for building dynamic forms
Home-page: https://opengui.readthedocs.io/en/0.9.8/
Download-URL: https://github.com/gaf3/opengui
Author: Gaffer Fitch
Author-email: opengui@gaf3.com
Classifier: Programming Language :: Python :: 3
Classifier: License :: OSI Approved :: MIT License
License-File: LICENSE.txt
Requires-Dist: yaes>=0.2.5
Requires-Dist: MarkupSafe==2.1.5
